Metadata-Version: 2.1
Name: InverterDB
Version: 0.1.0
Summary: Database with just the information for the inverters
Project-URL: Homepage, https://github.com/pypa/sampleproject
Project-URL: Bug Tracker, https://github.com/pypa/sampleproject/issues
Author-email: Pedro Vila Luz <pedro.vila.luz@gmail.com>
Classifier: License :: OSI Approved :: MIT License
Classifier: Operating System :: OS Independent
Classifier: Programming Language :: Python :: 3
Requires-Python: >=3.7
